SaltTesting-2018.9.21.data/scripts/github-commit-status
SaltTesting-2018.9.21.data/scripts/salt-jenkins-build
SaltTesting-2018.9.21.dist-info/METADATA
SaltTesting-2018.9.21.dist-info/RECORD
SaltTesting-2018.9.21.dist-info/WHEEL
SaltTesting-2018.9.21.dist-info/entry_points.txt
SaltTesting-2018.9.21.dist-info/top_level.txt
salttesting/__init__.py
salttesting/case.py
salttesting/github.py
salttesting/helpers.py
salttesting/jenkins.py
salttesting/mixins.py
salttesting/mock.py
salttesting/runtests.py
salttesting/unit.py
salttesting/version.py
salttesting/xmlunit.py
salttesting/cherrypytest/__init__.py
salttesting/cherrypytest/base.py
salttesting/cherrypytest/case.py
salttesting/ext/__init__.py
salttesting/ext/console.py
salttesting/ext/os_data.py
salttesting/parser/__init__.py
salttesting/parser/cover.py
salttesting/pylintplugins/__init__.py
salttesting/pylintplugins/fileperms.py
salttesting/pylintplugins/pep263.py
salttesting/pylintplugins/pep8.py
salttesting/pylintplugins/smartup.py
salttesting/pylintplugins/strings.py
salttesting/pylintplugins/py3modernize/__init__.py
salttesting/pylintplugins/py3modernize/fixes/__init__.py
salttesting/pylintplugins/py3modernize/fixes/fix_filter_salt_six.py
salttesting/pylintplugins/py3modernize/fixes/fix_imports_salt_six.py
salttesting/pylintplugins/py3modernize/fixes/fix_input_salt_six.py
salttesting/pylintplugins/py3modernize/fixes/fix_map_salt_six.py
salttesting/pylintplugins/py3modernize/fixes/fix_xrange_salt_six.py
salttesting/pylintplugins/py3modernize/fixes/fix_zip_salt_six.py
